README.md
setup.py
po2json/__init__.py
po2json.egg-info/PKG-INFO
po2json.egg-info/SOURCES.txt
po2json.egg-info/dependency_links.txt
po2json.egg-info/entry_points.txt
po2json.egg-info/not-zip-safe
po2json.egg-info/requires.txt
po2json.egg-info/top_level.txt