Metadata-Version: 1.1
Name: po2json
Version: 0.2.2
Summary: Converts gettext .po files to javascript objects
Home-page: https://github.com/eventray/po2json
Author: John Anderson
Author-email: sontek@gmail.com
License: BSD
Keywords: pyramid
Platform: UNKNOWN
Classifier: Intended Audience :: Developers
Classifier: License :: OSI Approved :: BSD License
Classifier: Operating System :: OS Independent
Classifier: Programming Language :: Python
Classifier: Topic :: Internet :: WWW/HTTP :: Dynamic Content
Classifier: Topic :: Software Development :: Libraries :: Python Modules
